{
    "$schema": "https://schema.management.azure.com/schemas/2015-01-01/deploymentParameters.json#",
    "contentVersion": "1.0.0.0",
    "parameters": {
        "name": {
            "value": "KV-MGTCLAKeyVault"
        },
        "location": {
            "value": "northeurope"
        },
        "sku": {
            "value": "Premium"
        },
        "accessPolicies": {
            "value": [
                {
                    "objectId": "09c30de2-f433-431a-b235-b7a7481e732d",
                    "tenantId": "1e69c6f2-788f-4977-b21e-acbf7e7ef62c",
                    "permissions": {
                        "keys": [
                            "Get",
                            "List",
                            "Update",
                            "Create",
                            "Import",
                            "Delete",
                            "Recover",
                            "Backup",
                            "Restore"
                        ],
                        "secrets": [
                            "Get",
                            "List",
                            "Set",
                            "Delete",
                            "Recover",
                            "Backup",
                            "Restore"
                        ],
                        "certificates": [
                            "Get",
                            "List",
                            "Update",
                            "Create",
                            "Import",
                            "Delete",
                            "Recover",
                            "ManageContacts",
                            "ManageIssuers",
                            "GetIssuers",
                            "ListIssuers",
                            "SetIssuers",
                            "DeleteIssuers"
                        ]
                    }
                }
            ]
        },
        "tenant": {
            "value": "1e69c6f2-788f-4977-b21e-acbf7e7ef62c"
        },
        "enabledForDeployment": {
            "value": true
        },
        "enabledForTemplateDeployment": {
            "value": true
        },
        "enabledForDiskEncryption": {
            "value": true
        }
    }
}